{
  "total": 1,
  "rows": [
    {
      "backDelivery": "OC-顺丰速运",
      "remark": "",
      "addressee": "黄先生",
      "innerRemark": "",
      "oldWareHouseName": "天马总仓1仓",
      "postage": 24,
      "isBackExpressNoExist": 0,
      "c_remark": "",
      "backExpressNo": "221505956141",
      "mapPath": "",
      "lastDealTime": "2017-12-04 13:18:34",
      "pickingDate": "2017-12-01 11:27:00",
      "exportFlag": null,
      "status": 2,
      "newWareHouseId": 0,
      "proxyId": 147424,
      "discountPrice": 334.89,
      "size": "43",
      "discount": 6.1,
      "problemContent": "退货 12-04 13:18<br/>",
      "delivery": "顺丰",
      "p_warehouse": "天马总仓1仓",
      "addTime": "2017-12-04 13:18:34",
      "commodityRefund": 0,
      "size1": "9.5",
      "id": 652927,
      "problemReply": "代理顾客收到不合适退总仓",
      "is_gai": 0,
      "oldWareHouseId": 182,
      "newWareHouseName": null,
      "exchangeNo": "",
      "articleno": "833411-401",
      "receiptTime": null,
      "orderId": 27269060,
      "postageDescr": "",
      "marketPrice": 549,
      "proxyName": "青岛麦巨商贸",
      "submitExpressNoTime": "2017-12-04 14:02:36",
      "outer_tid": null,
      "problemType": "无理由退货",
      "sysUserId": null,
      "totleRefund": 0,
      "backType": 0,
      "proxyOrderID": "100073063600492252",
      "postageRefund": 0,
      "sysUserName": null,
      "sendBackAddr": " 拒收圆通、快捷快递、百世汇通快递和所有邮局件包括EMS、小包和平邮    他们不给验货 如发邮局件商品有问题需自行承担   快捷快递不到 ，江苏省连云港市海州区浦南镇淘宝路8号仓  收件人： 朱铭红转渠道部 电话：18136575079 （此电话只用于接收快递电话，不处理售后问题） 退货建议发申通快递和顺丰，以及天天快递和中通快递！",
      "pay_price": null,
      "outer_order_id": null
    }
  ]
}